wd_fw_update/__init__.py
wd_fw_update/main.py
wd_fw_update-2.3.0.dist-info/METADATA
wd_fw_update-2.3.0.dist-info/WHEEL
wd_fw_update-2.3.0.dist-info/entry_points.txt
wd_fw_update-2.3.0.dist-info/top_level.txt
wd_fw_update-2.3.0.dist-info/RECORD
