Metadata-Version: 2.4
Name: wd_fw_update
Version: 2.3.0
Summary: Updates the firmware of Western Digital SSDs on Ubuntu / Linux Mint.
Home-page: https://github.com/not-a-feature/wd_fw_update
Author: Jules Kreuer
Author-email: contact@juleskreuer.eu
License: GPL-3.0-or-later
Project-URL: Documentation, https://github.com/not-a-feature/wd_fw_update
Project-URL: Source, https://github.com/not-a-feature/wd_fw_update
Project-URL: Changelog, https://github.com/not-a-feature/wd_fw_update/releases
Project-URL: Tracker, https://github.com/not-a-feature/wd_fw_update/issues
Project-URL: Download, https://pypi.org/project/wd_fw_update/
Platform: Mac
Platform: Linux
Classifier: Development Status :: 4 - Beta
Classifier: Programming Language :: Python
Requires-Python: >=3.8
Requires-Dist: importlib-metadata; python_version < "3.8"
Requires-Dist: inquirer<4,>=3
Requires-Dist: requests<3,>=2.2
Provides-Extra: testing
Requires-Dist: setuptools; extra == "testing"
